devart/dynamics365/__init__.py
devart/dynamics365/dynamics365.cp310-win_amd64.pyd
devart/dynamics365/dynamics365.pyi
devart/dynamics365/Dynamics365/Devart.Python.DynamicsEngine.dll
devart/dynamics365/Dynamics365/Devart.Python.DynamicsEngine.runtimeconfig.json
devart/dynamics365/Dynamics365/Microsoft.Bcl.AsyncInterfaces.dll
devart/dynamics365/Dynamics365/Microsoft.Crm.Sdk.Proxy.dll
devart/dynamics365/Dynamics365/Microsoft.Extensions.Caching.Abstractions.dll
devart/dynamics365/Dynamics365/Microsoft.Extensions.Caching.Memory.dll
devart/dynamics365/Dynamics365/Microsoft.Extensions.Configuration.Abstractions.dll
devart/dynamics365/Dynamics365/Microsoft.Extensions.Configuration.Binder.dll
devart/dynamics365/Dynamics365/Microsoft.Extensions.Configuration.dll
devart/dynamics365/Dynamics365/Microsoft.Extensions.DependencyInjection.Abstractions.dll
devart/dynamics365/Dynamics365/Microsoft.Extensions.DependencyInjection.dll
devart/dynamics365/Dynamics365/Microsoft.Extensions.Http.dll
devart/dynamics365/Dynamics365/Microsoft.Extensions.Logging.Abstractions.dll
devart/dynamics365/Dynamics365/Microsoft.Extensions.Logging.dll
devart/dynamics365/Dynamics365/Microsoft.Extensions.ObjectPool.dll
devart/dynamics365/Dynamics365/Microsoft.Extensions.Options.dll
devart/dynamics365/Dynamics365/Microsoft.Extensions.Primitives.dll
devart/dynamics365/Dynamics365/Microsoft.Identity.Client.Extensions.Msal.dll
devart/dynamics365/Dynamics365/Microsoft.Identity.Client.dll
devart/dynamics365/Dynamics365/Microsoft.PowerPlatform.Dataverse.Client.dll
devart/dynamics365/Dynamics365/Microsoft.Rest.ClientRuntime.dll
devart/dynamics365/Dynamics365/Microsoft.Xrm.Sdk.dll
devart/dynamics365/Dynamics365/Newtonsoft.Json.dll
devart/dynamics365/Dynamics365/System.Configuration.ConfigurationManager.dll
devart/dynamics365/Dynamics365/System.Diagnostics.PerformanceCounter.dll
devart/dynamics365/Dynamics365/System.Private.ServiceModel.dll
devart/dynamics365/Dynamics365/System.Runtime.Caching.dll
devart_dynamics365_connector-1.2.0.dist-info/LICENSE
devart_dynamics365_connector-1.2.0.dist-info/METADATA
devart_dynamics365_connector-1.2.0.dist-info/WHEEL
devart_dynamics365_connector-1.2.0.dist-info/top_level.txt
devart_dynamics365_connector-1.2.0.dist-info/RECORD
